Metadata-Version: 2.1
Name: seele
Version: 0.5.5
Summary: Website packaged for UF in Japan, Summer 2024
Home-page: https://github.com/JMalegni/DisasterPrepApp
Author: Nicholas DeSanctis, Joseph Malegni, Christian Ferrer, Logan Chenicek, Xael Font
Author-email: nickdesanctis17@gmail.com
Project-URL: Source, https://github.com/JMalegni/DisasterPrepApp
Classifier: Development Status :: 3 - Alpha
Classifier: Framework :: Django
Classifier: Programming Language :: Python :: 3
Classifier: Programming Language :: Python :: 3.8
License-File: LICENSE
Requires-Dist: django >=5.0.6
Requires-Dist: django-bootstrap4 >=23.4
Requires-Dist: sqlparse >=0.3.1
Requires-Dist: pillow >=10.3.0
Requires-Dist: requests >=2.32.3
Requires-Dist: bleach >=6.1.0
Requires-Dist: django-pwa >=1.1.0
Requires-Dist: gTTS >=2.5.2
